ingenialink/__init__.py
ingenialink/_version.py
ingenialink/bitfield.py
ingenialink/configuration_file.py
ingenialink/constants.py
ingenialink/csv_configuration_file.py
ingenialink/dictionary.py
ingenialink/drive_context_manager.py
ingenialink/emcy.py
ingenialink/exceptions.py
ingenialink/network.py
ingenialink/pdo.py
ingenialink/pdo_network_manager.py
ingenialink/poller.py
ingenialink/py.typed
ingenialink/register.py
ingenialink/servo.py
ingenialink/canopen/__init__.py
ingenialink/canopen/dictionary.py
ingenialink/canopen/network.py
ingenialink/canopen/register.py
ingenialink/canopen/servo.py
ingenialink/cython_files/CyGetAdaptersAddresses.pxd
ingenialink/cython_files/__init__.py
ingenialink/cython_files/get_adapters_addresses.pyx
ingenialink/enums/__init__.py
ingenialink/enums/register.py
ingenialink/enums/servo.py
ingenialink/eoe/__init__.py
ingenialink/eoe/network.py
ingenialink/ethercat/__init__.py
ingenialink/ethercat/dictionary.py
ingenialink/ethercat/network.py
ingenialink/ethercat/register.py
ingenialink/ethercat/servo.py
ingenialink/ethernet/__init__.py
ingenialink/ethernet/dictionary.py
ingenialink/ethernet/network.py
ingenialink/ethernet/register.py
ingenialink/ethernet/servo.py
ingenialink/utils/__init__.py
ingenialink/utils/_utils.py
ingenialink/utils/mcb.py
ingenialink/utils/timeout.py
ingenialink/utils/udp.py
ingenialink/virtual/__init__.py
ingenialink/virtual/dictionary.py
ingenialink/virtual/network.py
ingenialink/virtual/servo.py
virtual_drive/__init__.py
virtual_drive/constants.py
virtual_drive/core.py
virtual_drive/environment.py
virtual_drive/gpios.py
virtual_drive/py.typed
virtual_drive/signals.py
virtual_drive/resources/__init__.py
virtual_drive/resources/virtual_drive.xcf
virtual_drive/resources/virtual_drive.xdf
virtual_drive/resources/virtual_drive_v3.0.xdf
ingenialink-7.5.1.dist-info/LICENSE.md
ingenialink-7.5.1.dist-info/METADATA
ingenialink-7.5.1.dist-info/WHEEL
ingenialink-7.5.1.dist-info/top_level.txt
ingenialink-7.5.1.dist-info/RECORD
