Metadata-Version: 2.1
Name: ingenialink
Version: 7.5.1
Summary: IngeniaLink Communications Library
Home-page: https://www.ingeniamc.com
Author-email: Novanta <support@ingeniamc.com>
Project-URL: Documentation, https://distext.ingeniamc.com/doc/ingenialink-python/development
Project-URL: Source, https://github.com/ingeniamc/ingenialink-python
Classifier: Development Status :: 4 - Beta
Classifier: Intended Audience :: Developers
Classifier: Operating System :: OS Independent
Classifier: Programming Language :: Python :: 3
Classifier: Programming Language :: Python :: 3.9
Classifier: Programming Language :: Python :: 3.10
Classifier: Programming Language :: Python :: 3.11
Classifier: Programming Language :: Python :: 3.12
Classifier: Programming Language :: Cython
Classifier: Topic :: Communications
Classifier: Topic :: Software Development :: Libraries
Requires-Python: >=3.9
License-File: LICENSE.md
Requires-Dist: canopen==2.2.0
Requires-Dist: python-can==4.4.2
Requires-Dist: ingenialogger>=0.2.1
Requires-Dist: ping3==4.0.3
Requires-Dist: pysoem<1.2.0,>=1.1.11
Requires-Dist: numpy>=1.26.0
Requires-Dist: scipy==1.12.0
Requires-Dist: bitarray==2.9.2
Requires-Dist: multiping==1.1.2
